jcppkernel/__init__.py
jcppkernel/__main__.py
jcppkernel/code_processing.py
jcppkernel/external_header.py
jcppkernel/realtime_subprocess.py
jcppkernel/temp_file_processing.py
jcppkernel/resources/gcpph.hpp
jcppkernel/resources/master.cpp
jcppkernel/resources/basicf/dlfcn.h
jcppkernel/resources/basicf/mathdefs.hpp
jcppkernel/resources/basicf/rstdio.h
jcppkernel/resources/cppio/cppin.hpp
jcppkernel/resources/cppio/cppout.hpp
jupyter-cpp-kernel-03/__init__.py
jupyter-cpp-kernel-03/__main__.py
jupyter-cpp-kernel-03/kernel_spec/kernel.json
jupyter-cpp-kernel-03/kernel_spec/logo-32x32.png
jupyter-cpp-kernel-03/kernel_spec/logo-64x64.png
jupyter-cpp-kernel-03/kernel_spec/logo-svg.svg
jupyter-cpp-kernel-11/__init__.py
jupyter-cpp-kernel-11/__main__.py
jupyter-cpp-kernel-11/kernel_spec/kernel.json
jupyter-cpp-kernel-11/kernel_spec/logo-32x32.png
jupyter-cpp-kernel-11/kernel_spec/logo-64x64.png
jupyter-cpp-kernel-11/kernel_spec/logo-svg.svg
jupyter-cpp-kernel-14/__init__.py
jupyter-cpp-kernel-14/__main__.py
jupyter-cpp-kernel-14/kernel_spec/kernel.json
jupyter-cpp-kernel-14/kernel_spec/logo-32x32.png
jupyter-cpp-kernel-14/kernel_spec/logo-64x64.png
jupyter-cpp-kernel-14/kernel_spec/logo-svg.svg
jupyter-cpp-kernel-17/__init__.py
jupyter-cpp-kernel-17/__main__.py
jupyter-cpp-kernel-17/kernel_spec/kernel.json
jupyter-cpp-kernel-17/kernel_spec/logo-32x32.png
jupyter-cpp-kernel-17/kernel_spec/logo-64x64.png
jupyter-cpp-kernel-17/kernel_spec/logo-svg.svg
jupyter-cpp-kernel-20/__init__.py
jupyter-cpp-kernel-20/__main__.py
jupyter-cpp-kernel-20/kernel_spec/kernel.json
jupyter-cpp-kernel-20/kernel_spec/logo-32x32.png
jupyter-cpp-kernel-20/kernel_spec/logo-64x64.png
jupyter-cpp-kernel-20/kernel_spec/logo-svg.svg
jupyter-cpp-kernel-23/__init__.py
jupyter-cpp-kernel-23/__main__.py
jupyter-cpp-kernel-23/kernel_spec/kernel.json
jupyter-cpp-kernel-23/kernel_spec/logo-32x32.png
jupyter-cpp-kernel-23/kernel_spec/logo-64x64.png
jupyter-cpp-kernel-23/kernel_spec/logo-svg.svg
jupyter_cpp_kernel-1.0.0a9.dist-info/licenses/LICENSE
jupyter_cpp_kernel-1.0.0a9.dist-info/METADATA
jupyter_cpp_kernel-1.0.0a9.dist-info/WHEEL
jupyter_cpp_kernel-1.0.0a9.dist-info/top_level.txt
jupyter_cpp_kernel-1.0.0a9.dist-info/RECORD
