Metadata-Version: 2.4
Name: jupyter-cpp-kernel
Version: 1.0.0a9
Summary: C++ kernel for Jupyter
Home-page: https://github.com/shiroinekotfs/jupyter-cpp-kernel
Download-URL: https://github.com/shiroinekotfs/jupyter-cpp-kernel/releases
Author: shiroinekotfs
Author-email: shiroineko.tfs@gmail.com
License: MIT
Project-URL: Bug Tracker, https://github.com/shiroinekotfs/jupyter-cpp-kernel/issues
Keywords: windows,macos,linux,jupyter,cpp,jupyter-kernels,pip
Classifier: Programming Language :: Python :: 3
Classifier: Programming Language :: C++
Classifier: License :: OSI Approved :: MIT License
Classifier: Operating System :: Unix
Classifier: Operating System :: MacOS
Classifier: Operating System :: POSIX :: Linux
Classifier: Operating System :: Microsoft :: Windows
Requires-Python: >=3.9
License-File: LICENSE
Dynamic: author
Dynamic: author-email
Dynamic: classifier
Dynamic: download-url
Dynamic: home-page
Dynamic: keywords
Dynamic: license
Dynamic: license-file
Dynamic: summary
